odoo10_addon_stock_available_product_expiry-10.0.1.0.3.99.dev4-py3.8-nspkg.pth
odoo/addons/stock_available_product_expiry/README.rst
odoo/addons/stock_available_product_expiry/__init__.py
odoo/addons/stock_available_product_expiry/__manifest__.py
odoo/addons/stock_available_product_expiry/data/ir_config_parameter.xml
odoo/addons/stock_available_product_expiry/data/ir_sequence_data.xml
odoo/addons/stock_available_product_expiry/i18n/stock_available_product_expiry.pot
odoo/addons/stock_available_product_expiry/models/__init__.py
odoo/addons/stock_available_product_expiry/models/product_product.py
odoo/addons/stock_available_product_expiry/models/product_template.py
odoo/addons/stock_available_product_expiry/models/res_config.py
odoo/addons/stock_available_product_expiry/models/stock_production_lot.py
odoo/addons/stock_available_product_expiry/models/stock_scrap.py
odoo/addons/stock_available_product_expiry/models/stock_scrap_expired.py
odoo/addons/stock_available_product_expiry/models/stock_scrap_expired_line.py
odoo/addons/stock_available_product_expiry/readme/CONTRIBUTORS.rst
odoo/addons/stock_available_product_expiry/readme/DESCRIPTION.rst
odoo/addons/stock_available_product_expiry/readme/USAGE.rst
odoo/addons/stock_available_product_expiry/reports/stock_scrap_expired.xml
odoo/addons/stock_available_product_expiry/security/stock_scrap_expired.xml
odoo/addons/stock_available_product_expiry/security/stock_scrap_expired_line.xml
odoo/addons/stock_available_product_expiry/static/description/icon.png
odoo/addons/stock_available_product_expiry/static/description/index.html
odoo/addons/stock_available_product_expiry/static/src/less/stock_available_product_expiry.less
odoo/addons/stock_available_product_expiry/tests/__init__.py
odoo/addons/stock_available_product_expiry/tests/test_product_product.py
odoo/addons/stock_available_product_expiry/tests/test_product_template.py
odoo/addons/stock_available_product_expiry/tests/test_stock_scrap_expired.py
odoo10_addon_stock_available_product_expiry-10.0.1.0.3.99.dev4.dist-info/METADATA
odoo10_addon_stock_available_product_expiry-10.0.1.0.3.99.dev4.dist-info/WHEEL
odoo10_addon_stock_available_product_expiry-10.0.1.0.3.99.dev4.dist-info/namespace_packages.txt
odoo10_addon_stock_available_product_expiry-10.0.1.0.3.99.dev4.dist-info/top_level.txt
odoo10_addon_stock_available_product_expiry-10.0.1.0.3.99.dev4.dist-info/RECORD
